.ghlintrc
MANIFEST.in
README.rst
setup.py
ghlint/__init__.py
ghlint/__main__.py
ghlint/cli.py
ghlint/config.py
ghlint/lint.py
ghlint.egg-info/PKG-INFO
ghlint.egg-info/SOURCES.txt
ghlint.egg-info/dependency_links.txt
ghlint.egg-info/entry_points.txt
ghlint.egg-info/top_level.txt
tests/__init__.py
tests/test_config.py