Metadata-Version: 1.0
Name: ghlint
Version: 0.2.7
Summary: Linting utility for GitHub
Home-page: https://github.com/martinbuberl/ghlint
Author: Martin Buberl
Author-email: hello@martinbuberl.com
License: MIT
Platform: UNKNOWN
